{
  "__type__": "cc.JsonAsset",
  "_name": "level23",
  "_objFlags": 0,
  "_native": "",
  "json": {
    "path": [
      {
        "centerPos": {
          "x": 408,
          "y": 81
        },
        "startPos": {
          "x": 315,
          "y": 157
        },
        "endPos": {
          "x": 502,
          "y": 4
        },
        "blockSize": {
          "wid": 187,
          "hei": 153
        }
      },
      {
        "centerPos": {
          "x": 359,
          "y": -237
        },
        "startPos": {
          "x": 277,
          "y": -177
        },
        "endPos": {
          "x": 441,
          "y": -297
        },
        "blockSize": {
          "wid": 164,
          "hei": 120
        }
      },
      {
        "centerPos": {
          "x": 250,
          "y": -391
        },
        "startPos": {
          "x": 181,
          "y": -320
        },
        "endPos": {
          "x": 319,
          "y": -462
        },
        "blockSize": {
          "wid": 137,
          "hei": 142
        }
      },
      {
        "centerPos": {
          "x": 87,
          "y": -343
        },
        "startPos": {
          "x": 20,
          "y": -228
        },
        "endPos": {
          "x": 154,
          "y": -458
        },
        "blockSize": {
          "wid": 133,
          "hei": 229
        }
      },
      {
        "centerPos": {
          "x": -49,
          "y": -360
        },
        "startPos": {
          "x": -101,
          "y": -292
        },
        "endPos": {
          "x": 4,
          "y": -429
        },
        "blockSize": {
          "wid": 105,
          "hei": 136
        }
      },
      {
        "centerPos": {
          "x": -205,
          "y": -262
        },
        "startPos": {
          "x": -270,
          "y": -190
        },
        "endPos": {
          "x": -141,
          "y": -335
        },
        "blockSize": {
          "wid": 128,
          "hei": 145
        }
      },
      {
        "centerPos": {
          "x": -399,
          "y": -403
        },
        "startPos": {
          "x": -485,
          "y": -342
        },
        "endPos": {
          "x": -312,
          "y": -464
        },
        "blockSize": {
          "wid": 172,
          "hei": 121
        }
      },
      {
        "centerPos": {
          "x": -262,
          "y": -23
        },
        "startPos": {
          "x": -356,
          "y": 58
        },
        "endPos": {
          "x": -169,
          "y": -105
        },
        "blockSize": {
          "wid": 187,
          "hei": 162
        }
      },
      {
        "centerPos": {
          "x": -18,
          "y": 379
        },
        "startPos": {
          "x": -110,
          "y": 450
        },
        "endPos": {
          "x": 74,
          "y": 307
        },
        "blockSize": {
          "wid": 184,
          "hei": 143
        }
      },
      {
        "centerPos": {
          "x": -452,
          "y": 269
        },
        "startPos": {
          "x": -530,
          "y": 349
        },
        "endPos": {
          "x": -374,
          "y": 190
        },
        "blockSize": {
          "wid": 156,
          "hei": 159
        }
      }
    ]
  }
}